snowballing/__init__.py
snowballing/approaches.py
snowballing/collection_helpers.py
snowballing/common_places.py
snowballing/config.py
snowballing/config_helpers.py
snowballing/dbindex.py
snowballing/dbmanager.py
snowballing/graph.py
snowballing/jupyter_utils.py
snowballing/models.py
snowballing/operations.py
snowballing/rules.py
snowballing/scholar.py
snowballing/selenium_scholar.py
snowballing/snowballing.py
snowballing/strategies.py
snowballing/utils.py
snowballing/web.py
snowballing/bibtex/__init__.py
snowballing/bibtex/database/__init__.py
snowballing/bibtex/database/places.py
snowballing/bibtex/database/groups/__init__.py
snowballing/bibtex/database/groups/constants.py
snowballing/bibtex/database/groups/unrelated.py
snowballing/bibtex/database/groups/related/__init__.py
snowballing/bibtex/database/groups/related/noworkflow.py
snowballing/example/.gitignore
snowballing/example/Backward.ipynb
snowballing/example/Forward.ipynb
snowballing/example/Index.ipynb
snowballing/example/Insert.ipynb
snowballing/example/Progress.ipynb
snowballing/example/SearchScholar.ipynb
snowballing/example/Validate.ipynb
snowballing/example/__init__,py
snowballing/example/__init__.py
snowballing/example/database/__init__.py
snowballing/example/database/places.py
snowballing/example/database/citations/murta2014a.py
snowballing/example/database/groups/__init__.py
snowballing/example/database/groups/constants.py
snowballing/example/database/groups/unrelated.py
snowballing/example/database/groups/related/__init__.py
snowballing/example/database/groups/related/noworkflow.py
snowballing/example/database/work/y2008.py
snowballing/example/database/work/y2014.py
snowballing/example/database/work/y2015.py
snowballing/example/database/work/y9999.py
snowballing/example/files/murta2014a.pdf
snowballing/example/files/pimentel2015a.pdf
snowballing/example/notebooks/ApproachesHTML.ipynb
snowballing/example/notebooks/Bibtex.SearchWork.ipynb
snowballing/example/notebooks/CitationGraph.ipynb
Snowballing-1.0.2.dist-info/LICENSE
Snowballing-1.0.2.dist-info/METADATA
Snowballing-1.0.2.dist-info/WHEEL
Snowballing-1.0.2.dist-info/entry_points.txt
Snowballing-1.0.2.dist-info/top_level.txt
Snowballing-1.0.2.dist-info/RECORD
