Metadata-Version: 2.1
Name: Snowballing
Version: 1.0.2
Summary: Provides tools for literature snowballing
Home-page: https://github.com/JoaoFelipe/snowballing
Author: ('Joao Felipe Pimentel',)
Author-email: joaofelipenp@gmail.com
License: MIT
Keywords: snowballing literature paper article scholar
Platform: UNKNOWN
Classifier: Development Status :: 3 - Alpha
Classifier: Intended Audience :: Science/Research
Classifier: Topic :: Scientific/Engineering
Classifier: License :: OSI Approved :: MIT License
Classifier: Programming Language :: Python :: 3.5
Classifier: Programming Language :: Python :: 3.6
Requires-Python: >=3.5
Requires-Dist: ipython
Requires-Dist: jupyter
Requires-Dist: ipywidgets (>=7.4.2)
Requires-Dist: pyposast
Requires-Dist: svgwrite
Requires-Dist: bibtexparser (>=1.1.0)
Requires-Dist: bs4
Requires-Dist: selenium
Requires-Dist: matplotlib
Requires-Dist: pandas
Requires-Dist: seaborn
Requires-Dist: numpy
